kiarina/lib/cloudflare/d1/__init__.py
kiarina/lib/cloudflare/d1/_settings.py
kiarina/lib/cloudflare/d1/asyncio.py
kiarina/lib/cloudflare/d1/py.typed
kiarina/lib/cloudflare/d1/_async/__init__.py
kiarina/lib/cloudflare/d1/_async/helpers/__init__.py
kiarina/lib/cloudflare/d1/_async/helpers/create_d1_client.py
kiarina/lib/cloudflare/d1/_async/models/__init__.py
kiarina/lib/cloudflare/d1/_async/models/d1_client.py
kiarina/lib/cloudflare/d1/_core/__init__.py
kiarina/lib/cloudflare/d1/_core/models/__init__.py
kiarina/lib/cloudflare/d1/_core/models/d1_context.py
kiarina/lib/cloudflare/d1/_core/operations/__init__.py
kiarina/lib/cloudflare/d1/_core/operations/query.py
kiarina/lib/cloudflare/d1/_core/views/__init__.py
kiarina/lib/cloudflare/d1/_core/views/query_result.py
kiarina/lib/cloudflare/d1/_core/views/response_info.py
kiarina/lib/cloudflare/d1/_core/views/result.py
kiarina/lib/cloudflare/d1/_sync/__init__.py
kiarina/lib/cloudflare/d1/_sync/helpers/__init__.py
kiarina/lib/cloudflare/d1/_sync/helpers/create_d1_client.py
kiarina/lib/cloudflare/d1/_sync/models/__init__.py
kiarina/lib/cloudflare/d1/_sync/models/d1_client.py
kiarina_lib_cloudflare_d1-1.35.0.dist-info/METADATA
kiarina_lib_cloudflare_d1-1.35.0.dist-info/WHEEL
kiarina_lib_cloudflare_d1-1.35.0.dist-info/RECORD
